numba_hip/__init__.py
numba_hip-0.0.2.dist-info/METADATA
numba_hip-0.0.2.dist-info/WHEEL
numba_hip-0.0.2.dist-info/top_level.txt
numba_hip-0.0.2.dist-info/RECORD
