Metadata-Version: 2.4
Name: numba-hip
Version: 0.0.2
Summary: Numba HIP - Numba backend for AMD GPUs
Author-email: AMD <support@amd.com>
License: MIT
Project-URL: Homepage, https://github.com/rocm/numba-hip
Project-URL: Documentation, https://github.com/rocm/numba-hip
Requires-Python: >=3.8
